reea.py
reea-0.1.3.dist-info/METADATA
reea-0.1.3.dist-info/WHEEL
reea-0.1.3.dist-info/entry_points.txt
reea-0.1.3.dist-info/top_level.txt
reea-0.1.3.dist-info/RECORD
